dlcmapi_client/__init__.py
dlcmapi_client/api_client.py
dlcmapi_client/configuration.py
dlcmapi_client/exceptions.py
dlcmapi_client/rest.py
dlcmapi_client/api/__init__.py
dlcmapi_client/api/access_api.py
dlcmapi_client/api/admin_api.py
dlcmapi_client/api/archival_storage_api.py
dlcmapi_client/api/data_mgmt_api.py
dlcmapi_client/api/dlcm_api.py
dlcmapi_client/api/index_api.py
dlcmapi_client/api/ingest_api.py
dlcmapi_client/api/oai_info_api.py
dlcmapi_client/api/preingest_api.py
dlcmapi_client/api/preservation_planning_api.py
dlcmapi_client/models/__init__.py
dlcmapi_client/models/access.py
dlcmapi_client/models/access_organizational_unit.py
dlcmapi_client/models/admin.py
dlcmapi_client/models/aip.py
dlcmapi_client/models/aip_checksum_check.py
dlcmapi_client/models/aip_file_format.py
dlcmapi_client/models/aip_info.py
dlcmapi_client/models/aip_info_embargo.py
dlcmapi_client/models/aip_virus_check.py
dlcmapi_client/models/application.py
dlcmapi_client/models/application_role.py
dlcmapi_client/models/archival_storage.py
dlcmapi_client/models/archive_acl.py
dlcmapi_client/models/archive_acl_organizational_unit.py
dlcmapi_client/models/archive_acl_user.py
dlcmapi_client/models/archive_rating.py
dlcmapi_client/models/archive_rating_rating_type.py
dlcmapi_client/models/archive_rating_user.py
dlcmapi_client/models/archive_statistics.py
dlcmapi_client/models/archive_type.py
dlcmapi_client/models/change_info.py
dlcmapi_client/models/collection.py
dlcmapi_client/models/contributor.py
dlcmapi_client/models/data_mgmt.py
dlcmapi_client/models/deposit.py
dlcmapi_client/models/dip.py
dlcmapi_client/models/dissemination_policy.py
dlcmapi_client/models/funding_agency.py
dlcmapi_client/models/index.py
dlcmapi_client/models/index_field_alias.py
dlcmapi_client/models/ingest.py
dlcmapi_client/models/institution.py
dlcmapi_client/models/language.py
dlcmapi_client/models/licens.py
dlcmapi_client/models/metadata.py
dlcmapi_client/models/metadata_type.py
dlcmapi_client/models/module.py
dlcm_api-2.1.1.dist-info/METADATA
dlcm_api-2.1.1.dist-info/WHEEL
dlcm_api-2.1.1.dist-info/top_level.txt
dlcm_api-2.1.1.dist-info/RECORD
