Metadata-Version: 2.1
Name: dlcm-api
Version: 2.1.1
Summary: DLCM application wrapping all modules, All-In-One
Home-page: https://gitlab.unige.ch/dlcm/community/dlcm-python-api
Author: University of Geneva
Author-email: eresearch-opensource@unige.ch
License: GPL-2.0-or-later
Keywords: OpenAPI,OpenAPI-Generator,DLCM-Solution,Digital Preservation
Platform: UNKNOWN
Classifier: License :: OSI Approved :: GNU General Public License v2 or later (GPLv2+)
Classifier: Programming Language :: Python :: 3
Classifier: Operating System :: OS Independent
Classifier: Topic :: System :: Archiving
Requires-Dist: certifi
Requires-Dist: python-dateutil
Requires-Dist: six (>=1.10)
Requires-Dist: urllib3 (>=1.15)
